dc_overview/__init__.py
dc_overview/cli.py
dc_overview/config.py
dc_overview/deploy.py
dc_overview/exporters.py
dc_overview/quickstart.py
dc_overview/reverse_proxy.py
dc_overview/service.py
dc_overview/templates.py
dc_overview/wizard.py
dc_overview/templates/landing.html.j2
dc_overview/templates/nginx.conf.j2
dc_overview-1.0.9.dist-info/METADATA
dc_overview-1.0.9.dist-info/WHEEL
dc_overview-1.0.9.dist-info/entry_points.txt
dc_overview-1.0.9.dist-info/top_level.txt
dc_overview-1.0.9.dist-info/RECORD
