Metadata-Version: 2.4
Name: dc-overview
Version: 1.0.9
Summary: GPU Datacenter Monitoring Suite - Prometheus, Grafana & Exporters
Author-email: CryptoLabs <info@cryptolabs.co.za>
License: MIT
Project-URL: Homepage, https://github.com/cryptolabsza/dc-overview
Project-URL: Documentation, https://cryptolabs.co.za/dc-monitoring/
Project-URL: Repository, https://github.com/cryptolabsza/dc-overview
Project-URL: Issues, https://github.com/cryptolabsza/dc-overview/issues
Project-URL: Discord, https://discord.gg/7yeHdf5BuC
Keywords: gpu,datacenter,monitoring,prometheus,grafana,nvidia,dcgm,vast.ai
Classifier: Development Status :: 4 - Beta
Classifier: Environment :: Console
Classifier: Intended Audience :: System Administrators
Classifier: License :: OSI Approved :: MIT License
Classifier: Operating System :: POSIX :: Linux
Classifier: Programming Language :: Python :: 3
Classifier: Programming Language :: Python :: 3.9
Classifier: Programming Language :: Python :: 3.10
Classifier: Programming Language :: Python :: 3.11
Classifier: Programming Language :: Python :: 3.12
Classifier: Topic :: System :: Monitoring
Classifier: Topic :: System :: Systems Administration
Requires-Python: >=3.9
Requires-Dist: click>=8.1.0
Requires-Dist: rich>=13.0.0
Requires-Dist: questionary>=2.0.0
Requires-Dist: pyyaml>=6.0
Requires-Dist: requests>=2.31.0
Requires-Dist: jinja2>=3.0.0
Provides-Extra: dev
Requires-Dist: pytest>=7.0.0; extra == "dev"
Requires-Dist: black>=23.0.0; extra == "dev"
Requires-Dist: ruff>=0.1.0; extra == "dev"
